[
    {
        "title": "東華電子報 2023年0６月刊 ",
        "timestamp": "1688430945",
        "url": "mail_display.php?timestamp=1688430945",
        "date": "2023/07/04 08:35",
        "department": "秘書室公關宣傳組",
        "author": "林佩瑤",
        "content": "\u003cdiv class=\"column1-unit\"\u003e\n\n\u003c!--  信件內容   --\u003e\n\u003cpre\u003e分類： 其他公告\n來源： 秘書室公關宣傳組 - 林佩瑤 - peiyao@gms.ndhu.edu.tw - 電話6013\n對象： 全校教職員_全校學生\n標題： 東華電子報 2023年0６月刊 \n日期： Tue, 4 Jul 2023 08:35:45 +0800\n\u003c/pre\u003e\u003chr class=\"clear-contentunit\"/\u003e\n\n\n\u003cmeta charset=\"UTF-8\"/\u003e\n\u003cmeta http-equiv=\"X-UA-Compatible\" content=\"IE=edge,chrome=1\"/\u003e\n\u003cmeta name=\"robots\" content=\"all\"/\u003e\n\u003cmeta name=\"googlebot\" content=\"all\"/\u003e\n\u003cmeta name=\"applicable-device\" content=\"pc,mobile\"/\u003e\n\u003cmeta name=\"viewport\" content=\"width=device-width, initial-scale=0.9, maximum-scale=3.0\"/\u003e\n\u003cmeta property=\"og:site_name\" content=\"國立東華大學電子報\"/\u003e\n\u003cmeta property=\"og:title\" content=\"東華電子報 | 2023年06月刊 | 國立東華大學\"/\u003e\n\u003cmeta property=\"og:type\" content=\"website\"/\u003e\n\u003cmeta property=\"og:url\" content=\"http://dp.ndhu.edu.tw/epaper/\"/\u003e\n\u003cmeta property=\"og:image\" content=\"http://dp.ndhu.edu.tw/epaper/images/facebook_tag.jpg\"/\u003e\n\u003ctitle\u003e東華電子報 | 2023年06月刊 | 國立東華大學\u003c/title\u003e\n\u003clink rel=\"stylesheet\" href=\"/GlobalInclude/fishbecat.resetCSS.1.2.css\"/\u003e\n\u003cscript src=\"/GlobalInclude/jquery-1.12.4.min.js\"\u003e\u003c/script\u003e\n\u003cscript src=\"/GlobalInclude/jquery_DigitClock.js\" charset=\"UTF-8\"\u003e\u003c/script\u003e\n\u003cscript src=\"/GlobalInclude/goTop.js\" charset=\"UTF-8\"\u003e\u003c/script\u003e\n\u003c!--[if lt IE 9]\u003e\n\u003cscript src='/GlobalInclude/html5.js'\u003e\u003c/script\u003e\n\u003c![endif]--\u003e\n\n\n\u003cdiv class=\"wrap\" style=\"width:100%;max-width:1280px;padding-bottom:8rem;margin:0 auto;background:#F8D65151 url(https://rpage.ndhu.edu.tw/var/file/0/1000/img/8/NDHU_pheasant.png) center bottom no-repeat;\"\u003e\n\u003cheader style=\"position:relative;min-height:6rem;text-align:center;padding:10px;\"\u003e\n\u003ca class=\"logo\" href=\"https://rpage.ndhu.edu.tw/?Lang=zh-TW\" target=\"_blank\" title=\"OPEN：國立東華大學首頁\" style=\"float:left;width:180px;position:\"\u003e\n\u003cimg src=\"https://rpage.ndhu.edu.tw/var/file/0/1000/img/8/NDHU_Logo+Title.png\" alt=\"Logo.NDHU\" style=\"width:100%;\"/\u003e\n\u003c/a\u003e\n\n\u003csection style=\"font-size:15px;width:170px;float:right;\"\u003e\n\u003ca href=\"http://dp.ndhu.edu.tw/epaper/?202306\" target=\"_blank\" style=\"text-decoration:none;font-weight:normal;vertical-align:middle;float:right;display:list-item;list-style:outside;margin:0 0 0 2em;\"\u003e電子報網頁版\u003c/a\u003e\n\u003ca href=\"https://www.facebook.com/pages/%E5%9C%8B%E7%AB%8B%E6%9D%B1%E8%8F%AF%E5%A4%A7%E5%AD%B8-National-Dong-Hwa-University-Taiwan/363583078223\" target=\"_blank\" style=\"text-decoration:none;font-weight:normal;vertical-align:middle;float:right;display:list-item;list-style:outside;margin:0 0 0 2em;\"\u003e東華facebook\u003c/a\u003e\n\u003ca href=\"mailto:SPR@gms.ndhu.edu.tw?subject=【關於東華大學電子報】\" style=\"text-decoration:none;font-weight:normal;vertical-align:middle;float:right;display:list-item;list-style:outside;margin:0 0 0 2em;\"\u003e聯絡我們\u003c/a\u003e\n\u003ca href=\"https://www.ndhu.edu.tw/?Lang=zh-TW\" target=\"_blank\" style=\"text-decoration:none;font-weight:normal;vertical-align:middle;float:right;display:list-item;list-style:outside;margin:0 0 0 2em;\"\u003e東華首頁\u003c/a\u003e\n\u003c/section\u003e\n\n\u003ca class=\"siteTitle\" href=\"./\" target=\"_self\" title=\"東華電子報\" style=\"width:240px;\"\u003e\n\u003cimg src=\"https://rpage.ndhu.edu.tw/var/file/0/1000/img/8/ePaper_siteTitle.png\" alt=\"Site.Title\"/\u003e\n\u003c/a\u003e\n\n\u003csection style=\"width:100%;font-size:27px;clear:both;\"\u003e\u003cfont style=\"font:bold 135%/1em \u0026#34;lucida grande\u0026#34;, Verdana, Tahoma, Arial;color:maroon;margin:0 0.2em;\"\u003e2023\u003c/font\u003e年\u003cfont class=\"Num\" style=\"font:bold 135%/1em \u0026#34;lucida grande\u0026#34;, Verdana, Tahoma, Arial;color:maroon;margin:0 0.2em;\"\u003e06\u003c/font\u003e月刊\u003c/section\u003e\n\u003c/header\u003e\n\n\u003cmain style=\"padding:0 10px;\"\u003e\n\n\u003c!-- 行政與校務 --\u003e\n\u003c!--\n\u003csection class=\"A_schoolAdmin\" style='display:none;'\u003e\n\u003cimg src=\"https://rpage.ndhu.edu.tw/var/file/0/1000/img/8/Tag_schoolAdmin.png\" alt=\"行政與校務\" /\u003e\n\u003cul style=\"list-style-type:disc;margin:0 auto !important;padding:0 1em;\"\u003e\n\u003c/ul\u003e\n\u003c/section\u003e\n--\u003e\n\n\u003c!-- 東華小故事 --\u003e\n\u003csection class=\"B_miniStory\" style=\"background:white;padding:2px;margin-bottom:6px;border:1px solid Silver;font-size:20px;border-radius:0 18px;\"\u003e\n\u003cimg src=\"https://rpage.ndhu.edu.tw/var/file/0/1000/img/8/Tag_miniStory.png\" alt=\"東華小故事\"/\u003e\n\u003cul style=\"list-style-type:disc;margin:0 auto !important;padding:0 1em;\"\u003e\n\u003cli style=\"margin:0 0 0 1.5em;padding:0.1em 0;font-size:26px;line-height:1.35;border-bottom:1px dotted silver;background:none;color:#f99e1a;;\"\u003e\u003ca href=\"https://www.ndhu.edu.tw/p/406-1000-209931,r4956.php?Lang=zh-tw#Dyn_2_3\" target=\"_blank\" style=\"text-decoration:none;font-weight:normal;font-size:20px;\"\u003e第三次《續修花蓮縣志》編纂啟動～東華大學攜手花蓮縣政府、文化局紀錄花蓮另一個二十年記憶\u003c/a\u003e\u003c/li\u003e\n\u003cli style=\"margin:0 0 0 1.5em;padding:0.1em 0;font-size:26px;line-height:1.35;border-bottom:1px dotted silver;background:none;color:#f99e1a;;\"\u003e\u003ca href=\"https://www.ndhu.edu.tw/p/406-1000-209327,r4956.php?Lang=zh-tw#Dyn_2_3\" target=\"_blank\" style=\"text-decoration:none;font-weight:normal;font-size:20px;\"\u003e深化原轉意識，認識在地歷史－Cikasuan七腳川歷史走讀工作坊\u003c/a\u003e\u003c/li\u003e\n\u003c/ul\u003e\n\u003c/section\u003e\n\n\u003c!-- 學生榮譽榜 --\u003e\n\u003csection class=\"C_stuHonor\" style=\"background:white;padding:2px;margin-bottom:6px;border:1px solid Silver;font-size:20px;border-radius:0 18px;\"\u003e\n\u003cimg src=\"https://rpage.ndhu.edu.tw/var/file/0/1000/img/8/Tag_stuHonor.png\" alt=\"學生榮譽榜\"/\u003e\n\u003cul style=\"list-style-type:disc;margin:0 auto !important;padding:0 1em;\"\u003e\n\u003cli style=\"margin:0 0 0 1.5em;padding:0.1em 0;font-size:26px;line-height:1.35;border-bottom:1px dotted silver;background:none;color:#fee101;;\"\u003e\u003ca href=\"https://www.ndhu.edu.tw/p/406-1000-209961,r4956.php?Lang=zh-tw#Dyn_2_3\" target=\"_blank\" style=\"text-decoration:none;font-weight:normal;font-size:20px;\"\u003e水保局洄游農村競賽，東華學生團隊入圍數冠全臺\u003c/a\u003e\u003c/li\u003e\n\u003cli style=\"margin:0 0 0 1.5em;padding:0.1em 0;font-size:26px;line-height:1.35;border-bottom:1px dotted silver;background:none;color:#fee101;;\"\u003e\u003ca href=\"https://www.ndhu.edu.tw/p/406-1000-209890,r4956.php?Lang=zh-tw#Dyn_2_3\" target=\"_blank\" style=\"text-decoration:none;font-weight:normal;font-size:20px;\"\u003e第三屆創新創業競賽國立東華大學囊括雙料優勝\u003c/a\u003e\u003c/li\u003e\n\u003cli style=\"margin:0 0 0 1.5em;padding:0.1em 0;font-size:26px;line-height:1.35;border-bottom:1px dotted silver;background:none;color:#fee101;;\"\u003e\u003ca href=\"https://www.ndhu.edu.tw/p/406-1000-209627,r4956.php?Lang=zh-tw#Dyn_2_3\" target=\"_blank\" style=\"text-decoration:none;font-weight:normal;font-size:20px;\"\u003e東華大學人社院舉辦第23屆東華奇萊文學獎頒獎典禮\u003c/a\u003e\u003c/li\u003e\n\u003cli style=\"margin:0 0 0 1.5em;padding:0.1em 0;font-size:26px;line-height:1.35;border-bottom:1px dotted silver;background:none;color:#fee101;;\"\u003e\u003ca href=\"https://www.ndhu.edu.tw/p/406-1000-209419,r4956.php?Lang=zh-tw#Dyn_2_3\" target=\"_blank\" style=\"text-decoration:none;font-weight:normal;font-size:20px;\"\u003e東華大學語傳系112級畢展「煙源」圓滿成功\u003c/a\u003e\u003c/li\u003e\n\u003c/ul\u003e\n\u003c/section\u003e\n\n\u003c!-- 學術榮耀 --\u003e\n\u003csection class=\"D_Glory\" style=\"background:white;padding:2px;margin-bottom:6px;border:1px solid Silver;font-size:20px;border-radius:0 18px;\"\u003e\n\u003cimg src=\"https://rpage.ndhu.edu.tw/var/file/0/1000/img/8/Tag_Glory.png\" alt=\"學術榮耀\"/\u003e\n\u003cul style=\"list-style-type:disc;margin:0 auto !important;padding:0 1em;\"\u003e\n\u003cli style=\"margin:0 0 0 1.5em;padding:0.1em 0;font-size:26px;line-height:1.35;border-bottom:1px dotted silver;background:none;color:#b5d04f;;\"\u003e\u003ca href=\"https://www.ndhu.edu.tw/p/406-1000-209471,r4956.php?Lang=zh-tw#Dyn_2_3\" target=\"_blank\" style=\"text-decoration:none;font-weight:normal;font-size:20px;\"\u003e2023 THE世界大學影響力排名，東華大學二項名列全球百大\u003c/a\u003e\u003c/li\u003e\n\u003cli style=\"margin:0 0 0 1.5em;padding:0.1em 0;font-size:26px;line-height:1.35;border-bottom:1px dotted silver;background:none;color:#b5d04f;;\"\u003e\u003ca href=\"https://www.ndhu.edu.tw/p/406-1000-209266,r4956.php?Lang=zh-tw#Dyn_2_3\" target=\"_blank\" style=\"text-decoration:none;font-weight:normal;font-size:20px;\"\u003e太平洋畔的插畫展～東華大學藝創系創意插畫在維納斯藝廊展出\u003c/a\u003e\u003c/li\u003e\n\u003c/ul\u003e\n\u003c/section\u003e\n\n\u003c!-- 學術交流 --\u003e\n\u003csection class=\"E_Contact\" style=\"background:white;padding:2px;margin-bottom:6px;border:1px solid Silver;font-size:20px;border-radius:0 18px;\"\u003e\n\u003cimg src=\"https://rpage.ndhu.edu.tw/var/file/0/1000/img/8/Tag_Contact.png\" alt=\"學術交流\"/\u003e\n\u003cul style=\"list-style-type:disc;margin:0 auto !important;padding:0 1em;\"\u003e\n\u003cli style=\"margin:0 0 0 1.5em;padding:0.1em 0;font-size:26px;line-height:1.35;border-bottom:1px dotted silver;background:none;color:#5ac6d0;;\"\u003e\u003ca href=\"https://www.ndhu.edu.tw/p/406-1000-209960,r4956.php?Lang=zh-tw#Dyn_2_3\" target=\"_blank\" style=\"text-decoration:none;font-weight:normal;font-size:20px;\"\u003e「2023 EMI 高峰論壇：英語及雙語教育與EMI的距離」圓滿落幕\u003c/a\u003e\u003c/li\u003e\n\u003cli style=\"margin:0 0 0 1.5em;padding:0.1em 0;font-size:26px;line-height:1.35;border-bottom:1px dotted silver;background:none;color:#5ac6d0;;\"\u003e\u003ca href=\"https://www.ndhu.edu.tw/p/406-1000-209952,r4956.php?Lang=zh-tw#Dyn_2_3\" target=\"_blank\" style=\"text-decoration:none;font-weight:normal;font-size:20px;\"\u003e東華大學教行系辦理2023數學直播共學暨國中繁星培育營\u003c/a\u003e\u003c/li\u003e\n\u003cli style=\"margin:0 0 0 1.5em;padding:0.1em 0;font-size:26px;line-height:1.35;border-bottom:1px dotted silver;background:none;color:#5ac6d0;;\"\u003e\u003ca href=\"https://www.ndhu.edu.tw/p/406-1000-209938,r4956.php?Lang=zh-tw#Dyn_2_3\" target=\"_blank\" style=\"text-decoration:none;font-weight:normal;font-size:20px;\"\u003e英國中央蘭開夏大學師生訪東華大學，互動交流開創合作未來\u003c/a\u003e\u003c/li\u003e\n\u003cli style=\"margin:0 0 0 1.5em;padding:0.1em 0;font-size:26px;line-height:1.35;border-bottom:1px dotted silver;background:none;color:#5ac6d0;;\"\u003e\u003ca href=\"https://www.ndhu.edu.tw/p/406-1000-209894,r4956.php?Lang=zh-tw#Dyn_2_3\" target=\"_blank\" style=\"text-decoration:none;font-weight:normal;font-size:20px;\"\u003e東華大學國際事務中心辦理原住民族國際學術交流，積極彰顯全球夥伴\u003c/a\u003e\u003c/li\u003e\n\u003cli style=\"margin:0 0 0 1.5em;padding:0.1em 0;font-size:26px;line-height:1.35;border-bottom:1px dotted silver;background:none;color:#5ac6d0;;\"\u003e\u003ca href=\"https://www.ndhu.edu.tw/p/406-1000-209808,r4956.php?Lang=zh-tw#Dyn_2_3\" target=\"_blank\" style=\"text-decoration:none;font-weight:normal;font-size:20px;\"\u003e東華大學社會學系社會實踐課程邀請業師評審，獲得業師一致肯定，實踐東華大學在地深耕的精神\u003c/a\u003e\u003c/li\u003e\n\u003cli style=\"margin:0 0 0 1.5em;padding:0.1em 0;font-size:26px;line-height:1.35;border-bottom:1px dotted silver;background:none;color:#5ac6d0;;\"\u003e\u003ca href=\"https://www.ndhu.edu.tw/p/406-1000-209628,r4956.php?Lang=zh-tw#Dyn_2_3\" target=\"_blank\" style=\"text-decoration:none;font-weight:normal;font-size:20px;\"\u003e東華大學社會學系社會實踐課程製作《光華村文史田野繪本》，發揮大學社會責任精神\u003c/a\u003e\u003c/li\u003e\n\u003cli style=\"margin:0 0 0 1.5em;padding:0.1em 0;font-size:26px;line-height:1.35;border-bottom:1px dotted silver;background:none;color:#5ac6d0;;\"\u003e\u003ca href=\"https://www.ndhu.edu.tw/p/406-1000-209500,r4956.php?Lang=zh-tw#Dyn_2_3\" target=\"_blank\" style=\"text-decoration:none;font-weight:normal;font-size:20px;\"\u003e東華大學經濟學系企業參訪證券交易所獲益良多\u003c/a\u003e\u003c/li\u003e\n\u003c/ul\u003e\n\u003c/section\u003e\n\n\u003c!-- 校園活動 --\u003e\n\u003csection class=\"F_Activity\" style=\"background:white;padding:2px;margin-bottom:6px;border:1px solid Silver;font-size:20px;border-radius:0 18px;\"\u003e\n\u003cimg src=\"https://rpage.ndhu.edu.tw/var/file/0/1000/img/8/Tag_Activity.png\" alt=\"校園活動\"/\u003e\n\u003cul style=\"list-style-type:disc;margin:0 auto !important;padding:0 1em;\"\u003e\n\u003cli style=\"margin:0 0 0 1.5em;padding:0.1em 0;font-size:26px;line-height:1.35;border-bottom:1px dotted silver;background:none;color:#46829d;;\"\u003e\u003ca href=\"https://www.ndhu.edu.tw/p/406-1000-209930,r4956.php?Lang=zh-tw#Dyn_2_3\" target=\"_blank\" style=\"text-decoration:none;font-weight:normal;font-size:20px;\"\u003e東華樂齡大學「舞動樂齡，活躍銀光」結業成果發表會，學員創意舞蹈表演，連結教育電台FB直播，樂在學習忘記年齡\u003c/a\u003e\u003c/li\u003e\n\u003cli style=\"margin:0 0 0 1.5em;padding:0.1em 0;font-size:26px;line-height:1.35;border-bottom:1px dotted silver;background:none;color:#46829d;;\"\u003e\u003ca href=\"https://www.ndhu.edu.tw/p/406-1000-209824,r4956.php?Lang=zh-tw#Dyn_2_3\" target=\"_blank\" style=\"text-decoration:none;font-weight:normal;font-size:20px;\"\u003e2023HSH創新創業競賽，大膽創新、勇於實踐，歡迎一起來觀賽、參加創業市集\u003c/a\u003e\u003c/li\u003e\n\u003cli style=\"margin:0 0 0 1.5em;padding:0.1em 0;font-size:26px;line-height:1.35;border-bottom:1px dotted silver;background:none;color:#46829d;;\"\u003e\u003ca href=\"https://www.ndhu.edu.tw/p/406-1000-209769,r4956.php?Lang=zh-tw#Dyn_2_3\" target=\"_blank\" style=\"text-decoration:none;font-weight:normal;font-size:20px;\"\u003e東華大學112年度師資生實踐史懷哲精神教育營隊授旗，造福偏鄉學童\u003c/a\u003e\u003c/li\u003e\n\u003cli style=\"margin:0 0 0 1.5em;padding:0.1em 0;font-size:26px;line-height:1.35;border-bottom:1px dotted silver;background:none;color:#46829d;;\"\u003e\u003ca href=\"https://www.ndhu.edu.tw/p/406-1000-209768,r4956.php?Lang=zh-tw#Dyn_2_3\" target=\"_blank\" style=\"text-decoration:none;font-weight:normal;font-size:20px;\"\u003e那些年學校沒教的大小事！翻轉花蓮國民小學月經教育，青春期免驚！友善性別校園，月經教育不可少\u003c/a\u003e\u003c/li\u003e\n\u003cli style=\"margin:0 0 0 1.5em;padding:0.1em 0;font-size:26px;line-height:1.35;border-bottom:1px dotted silver;background:none;color:#46829d;;\"\u003e\u003ca href=\"https://www.ndhu.edu.tw/p/406-1000-209564,r4956.php?Lang=zh-tw#Dyn_2_3\" target=\"_blank\" style=\"text-decoration:none;font-weight:normal;font-size:20px;\"\u003e東華大學通識教育教育大師講座：從武癡到武醫之路\u003c/a\u003e\u003c/li\u003e\n\u003cli style=\"margin:0 0 0 1.5em;padding:0.1em 0;font-size:26px;line-height:1.35;border-bottom:1px dotted silver;background:none;color:#46829d;;\"\u003e\u003ca href=\"https://www.ndhu.edu.tw/p/406-1000-209535,r4956.php?Lang=zh-tw#Dyn_2_3\" target=\"_blank\" style=\"text-decoration:none;font-weight:normal;font-size:20px;\"\u003e「用影像關注性別議題－成果展」看見多元性別，回應差異化族群！\u003c/a\u003e\u003c/li\u003e\n\u003cli style=\"margin:0 0 0 1.5em;padding:0.1em 0;font-size:26px;line-height:1.35;border-bottom:1px dotted silver;background:none;color:#46829d;;\"\u003e\u003ca href=\"https://www.ndhu.edu.tw/p/406-1000-209496,r4956.php?Lang=zh-tw#Dyn_2_3\" target=\"_blank\" style=\"text-decoration:none;font-weight:normal;font-size:20px;\"\u003e東華大學通識教育大師典範講座：科技與文化交融的文化創新故宮\u003c/a\u003e\u003c/li\u003e\n\u003cli style=\"margin:0 0 0 1.5em;padding:0.1em 0;font-size:26px;line-height:1.35;border-bottom:1px dotted silver;background:none;color:#46829d;;\"\u003e\u003ca href=\"https://www.ndhu.edu.tw/p/406-1000-209495,r4956.php?Lang=zh-tw#Dyn_2_3\" target=\"_blank\" style=\"text-decoration:none;font-weight:normal;font-size:20px;\"\u003e111－2通識教育中心手作活動：初夏簡單縫（驅蚊包實作）\u003c/a\u003e\u003c/li\u003e\n\u003cli style=\"margin:0 0 0 1.5em;padding:0.1em 0;font-size:26px;line-height:1.35;border-bottom:1px dotted silver;background:none;color:#46829d;;\"\u003e\u003ca href=\"https://www.ndhu.edu.tw/p/406-1000-209469,r4956.php?Lang=zh-tw#Dyn_2_3\" target=\"_blank\" style=\"text-decoration:none;font-weight:normal;font-size:20px;\"\u003e東華生活新元「宿」－吉爾吉斯坦：走進神祕古絲路\u003c/a\u003e\u003c/li\u003e\n\u003cli style=\"margin:0 0 0 1.5em;padding:0.1em 0;font-size:26px;line-height:1.35;border-bottom:1px dotted silver;background:none;color:#46829d;;\"\u003e\u003ca href=\"https://www.ndhu.edu.tw/p/406-1000-209463,r4956.php?Lang=zh-tw#Dyn_2_3\" target=\"_blank\" style=\"text-decoration:none;font-weight:normal;font-size:20px;\"\u003e產業走入學校「半導體IC載板產業實務人才培育專班」學生畢業即就業\u003c/a\u003e\u003c/li\u003e\n\u003cli style=\"margin:0 0 0 1.5em;padding:0.1em 0;font-size:26px;line-height:1.35;border-bottom:1px dotted silver;background:none;color:#46829d;;\"\u003e\u003ca href=\"https://www.ndhu.edu.tw/p/406-1000-209361,r4956.php?Lang=zh-tw#Dyn_2_3\" target=\"_blank\" style=\"text-decoration:none;font-weight:normal;font-size:20px;\"\u003e培育、成長與傳承－東華大學新航之舟啟航啦\u003c/a\u003e\u003c/li\u003e\n\u003cli style=\"margin:0 0 0 1.5em;padding:0.1em 0;font-size:26px;line-height:1.35;border-bottom:1px dotted silver;background:none;color:#46829d;;\"\u003e\u003ca href=\"https://www.ndhu.edu.tw/p/406-1000-209357,r4956.php?Lang=zh-tw#Dyn_2_3\" target=\"_blank\" style=\"text-decoration:none;font-weight:normal;font-size:20px;\"\u003e說故事也能拯救海洋！用英文遊戲與繪本開啟永續海洋教育\u003c/a\u003e\u003c/li\u003e\n\u003cli style=\"margin:0 0 0 1.5em;padding:0.1em 0;font-size:26px;line-height:1.35;border-bottom:1px dotted silver;background:none;color:#46829d;;\"\u003e\u003ca href=\"https://www.ndhu.edu.tw/p/406-1000-209354,r4956.php?Lang=zh-tw#Dyn_2_3\" target=\"_blank\" style=\"text-decoration:none;font-weight:normal;font-size:20px;\"\u003e書藝潛能社群推動書法教育不遺餘力，以多元創新教學模組開發寫字潛力\u003c/a\u003e\u003c/li\u003e\n\u003cli style=\"margin:0 0 0 1.5em;padding:0.1em 0;font-size:26px;line-height:1.35;border-bottom:1px dotted silver;background:none;color:#46829d;;\"\u003e\u003ca href=\"https://www.ndhu.edu.tw/p/406-1000-209267,r4956.php?Lang=zh-tw#Dyn_2_3\" target=\"_blank\" style=\"text-decoration:none;font-weight:normal;font-size:20px;\"\u003e東華大學致力於聯合國永續發展目標辦理「打開新視界，舒壓好方按」活動\u003c/a\u003e\u003c/li\u003e\n\u003cli style=\"margin:0 0 0 1.5em;padding:0.1em 0;font-size:26px;line-height:1.35;border-bottom:1px dotted silver;background:none;color:#46829d;;\"\u003e\u003ca href=\"https://www.ndhu.edu.tw/p/406-1000-209265,r4956.php?Lang=zh-tw#Dyn_2_3\" target=\"_blank\" style=\"text-decoration:none;font-weight:normal;font-size:20px;\"\u003e東華大學師培中心X光復科技中心－資訊科技教案研發分享暨研習圓滿成功\u003c/a\u003e\u003c/li\u003e\n\u003c/ul\u003e\n\u003c/section\u003e\n\n\u003c!-- 轉載分享 --\u003e\n\u003csection class=\"G_Share\" style=\"display:none;\"\u003e\n\u003cimg src=\"https://rpage.ndhu.edu.tw/var/file/0/1000/img/8/Tag_Share.png\" alt=\"轉載分享\"/\u003e\n\u003cul style=\"margin:0 auto !important; padding:0 1em;\"\u003e\n\u003cli style=\"list-style:none;padding:0 0 0.25em 1.6rem;margin:0.5em 0;line-height:1.3;border-bottom:1px dotted silver;background:url(http://dp.ndhu.edu.tw/epaper/images/icon_Sun_Purple.jpg)left top no-repeat;\"\u003e\u003ca href=\"http://faculty.ndhu.edu.tw/~LCenews/e_paper/e_paper.php\" target=\"_blank\" style=\"text-decoration:none;font-weight:normal;\"\u003e【左岸電子報】\u003c/a\u003e\u003c/li\u003e\n\u003c/ul\u003e\n\u003c/section\u003e\n\u003c/main\u003e\n\n\u003c!--編輯區 End--\u003e\n\u003cfooter style=\"color:darkgreen;text-align:center;font-size:15px;padding:5px;\"\u003e\n© \u003ca href=\"https://rpage.ndhu.edu.tw/?Lang=zh-TW\" target=\"_blank\" style=\"text-decoration:none;color:darkolivegreen;\"\u003e國立東華大學 NDHU, National Dong Hwa University\u003c/a\u003e\u003cbr/\u003e\n【\u003ca href=\"https://secret.ndhu.edu.tw/\" target=\"_blank\" style=\"text-decoration:none;color:darkolivegreen;\"\u003e秘書室公關宣傳組\u003c/a\u003e、\u003ca href=\"https://lic.ndhu.edu.tw/\" target=\"_blank\" style=\"text-decoration:none;color:darkolivegreen;\"\u003e圖書資訊處\u003c/a\u003e】製作\n\u003csup style=\"font-size:80%;color:chocolate;\"\u003e30\u003c/sup\u003e\u003c/footer\u003e\n\u003c/div\u003e\n\n\n\n\t\t\n\u003c/div\u003e"
    }
]