[
    {
        "title": "本校針對11月29日校級教師評審委員會衝突事件之說明",
        "timestamp": "1701310342",
        "url": "mail_display.php?timestamp=1701310342",
        "date": "2023/11/30 10:12",
        "department": "秘書室公關宣傳組",
        "author": "陳傳智",
        "content": "\u003cdiv class=\"column1-unit\"\u003e\n\n\u003c!--  信件內容   --\u003e\n\u003cpre\u003e分類： 行政公告\n來源： 秘書室公關宣傳組 - 陳傳智 - SPR@gms.ndhu.edu.tw - 電話6012\n對象： 全校教職員\n標題： 本校針對11月29日校級教師評審委員會衝突事件之說明\n日期： Thu, 30 Nov 2023 10:12:22 +0800\n\u003c/pre\u003e\u003chr class=\"clear-contentunit\"/\u003e\u003cpre\u003e針對昨日(11/29)在校級教師評審委員會發生的衝突事件，學校對此深表遺憾。依本校「教師申訴評議委員會組織及評議要點」第三點規定：申訴評議委員會委員應有本校教師會代表1人，然自112-1學期起，因教師會代表請辭後，該會遲未指派代表參與申訴評議委員會，使各類重要攸關教師權益的相關案件因被積壓而無法處理，導致申訴案當事者不滿，而在本次教評會（因陳情案）發生衝突事件。學校將會以嚴正的態度來處理昨日衝突事件，將蒐集資料，將肇事者移送法辦，並採取公正的態度來審理教師權益相關事宜。\n                                                                                 秘書室 敬啟\n\u003c/pre\u003e\n\t\t\n\u003c/div\u003e"
    }
]