[
    {
        "title": "代轉發~技術服務中心徵聘校務基金專任助理資訊",
        "timestamp": "1704179376",
        "url": "mail_display.php?timestamp=1704179376",
        "date": "2024/01/02 15:09",
        "department": "貴重儀器使用中心",
        "author": "汪小姐",
        "content": "\u003cdiv class=\"column1-unit\"\u003e\n\n\u003c!--  信件內容   --\u003e\n\u003cpre\u003e分類： 人事徵才\n來源： 貴重儀器使用中心 - 汪小姐 - ndhuprdc@gms.ndhu.edu.tw - 電話3972\n對象： 全校教職員\n標題： 代轉發~技術服務中心徵聘校務基金專任助理資訊\n日期： Tue, 2 Jan 2024 15:09:36 +0800\n\u003c/pre\u003e\u003chr class=\"clear-contentunit\"/\u003e\u003cpre\u003e【徵才】國立東華大學技術服務中心徵聘校務基金專任助理一名\n\n【職缺】技術服務中心專任助理 \n【起聘日期】113 年 2 月 1 日起 \n【工作地點】國立東華大學壽豐校區。\n【資格條件】\n1.\t具獲教育部認可之高中（含）以上學歷。\n2.\t嫻熟電腦文書處理、公文撰寫、基本網頁製作及維護能力。。\n3.\t具大學行政助理相關經驗優先考量。\n4.\t個性主動積極、負責及溝通協調能力，能獨立作業者。\n\n【工作內容】 \n1.\t協助中心各項行政業務。 \n2.\t公文及帳務處理、網頁維護。\n3.\t活動辦理及支援或其他交辦事項。\n\n【薪資待遇】\n  依「校務基金進用工作人員僱用要點」學歷職級標準，自基本工資台幣27,470元，最高至學士\n  第1級290薪點(折合台幣為32,933元)起敘，試用期2個月。\n\n【應徵資料】無限定履歷格式，請將其整理成同一份檔案\n1.\t中文履歷（含自傳並檢附個人照片）。\n2.\t最高學歷證明文件。 \n3.\t其他專業能力證明文件。\n \n【聯絡方式及注意事項】 \n1.\t意者請備齊相關資料於113年1月10日中午12點前以電子郵件方式郵寄應徵資料，（信箱：ndhuprdc@gms.ndhu.edu.tw），無須寄送紙本，逾時不予受理。\n2.\t電子郵件主旨請註明「應徵技術服務中心專任助理」字樣。\n3.\t資歷審查通過者，將以電話通知，敬請留意來電。不合者恕不另行通知或退件，亦不函復通知。\n4.\t聯絡人:蔡小姐，電話：03-8905228\n\u003c/pre\u003e\n\t\t\n\u003c/div\u003e"
    }
]