[
    {
        "title": "英國留學資訊分享會--世界百大名校諾丁漢大學推廣",
        "timestamp": "1709891183",
        "url": "mail_display.php?timestamp=1709891183",
        "date": "2024/03/08 17:46",
        "department": "國際事務處國際合作組",
        "author": "陳良愛",
        "content": "\u003cdiv class=\"column1-unit\"\u003e\n\n\u003c!--  信件內容   --\u003e\n\u003cpre\u003e分類： 活動公告\n來源： 國際事務處國際合作組 - 陳良愛 - ice@gms.ndhu.edu.tw - 電話5107\n對象： 全校學生\n標題： 英國留學資訊分享會--世界百大名校諾丁漢大學推廣\n日期： Fri, 8 Mar 2024 17:46:23 +0800\n附檔： \u003ca href=\"./message_7/1709891183/Want%20to%20study%20abroad.jpg\" target=\"_blank\"\u003eWant to study abroad.jpg\u003c/a\u003e (2 MB)   \u003c/pre\u003e\u003chr class=\"clear-contentunit\"/\u003e\u003cpre\u003e諾丁漢大學，是一所校址位於英國英格蘭中部地區諾丁漢郡的公立頂尖研究型大學，初創於1881年，作為倫敦大學的附屬學院並透過倫敦大學名義頒給證書，於1948年奉皇家特許升格為一所獨立的國立大學，屬於九所紅磚大學之一。諾丁漢大學分為五個學院，並提供各種科學和人文科學的約50種學位，且是英國申請最激烈的大學之一。\n\n國際處特別邀請諾丁漢大學主講本場次留學資訊分享會，Ms. Julie Zhu將與我們分享諾丁漢大學的校園資訊及在英國學習生活的二三事，歡迎有意了解英國留學資訊的同學們踴躍參加！\n\n日期：3月14日\n時間：12:15 PM - 1:15 PM\n地點：行政大樓 301室\n報名網址：\u003ca href=\"https://sys.ndhu.edu.tw/SA/XSL_ApplyRWD/ActAnnounce.aspx?ActID=20595\" target=\"_blank\"\u003ehttps://sys.ndhu.edu.tw/SA/XSL_ApplyRWD/ActAnnounce.aspx?ActID=20595\u003c/a\u003e\u003c/pre\u003e\u003chr/\u003ejpg、png、gif、pdf 附檔縮圖（pdf 只顯示第一頁）：\u003cp\u003e\u003c/p\u003e\u003cdiv style=\"text-align:center;display:inline-block;margin-right:20px;\"\u003e\u003ca href=\"./message_7/1709891183/Want%20to%20study%20abroad.jpg\" target=\"_blank\"\u003e\u003cimg src=\"./thumb/1709891183_Want to study abroad.jpg\"/\u003e\u003c/a\u003e\u003cbr/\u003eWant to study abroad.jpg\u003c/div\u003e\n\t\t\n\u003c/div\u003e"
    }
]