{
    "title": "諮商中心資源教室：【身心障礙者就業資源盤點與就業服務分享講座(場次一)】",
    "timestamp": "1725839702",
    "url": "mail_display.php?timestamp=1725839702",
    "date": "2024/09/09 07:55",
    "department": "心理諮商輔導中心 資源開發組",
    "author": {
        "department": "心理諮商輔導中心 資源開發組",
        "name": "鍾雅琳",
        "email": "lin.chung@gms.ndhu.edu.tw",
        "phone": "03-8903155"
    },
    "content": "\u003cdiv class=\"column1-unit\"\u003e\n\n\u003c!--  信件內容   --\u003e\n\u003cpre\u003e分類： 活動公告\n來源： 心理諮商輔導中心 資源開發組 - 鍾雅琳 - lin.chung@gms.ndhu.edu.tw - 電話03-8903155\n對象： 全校學生_大一_大二_大三_大四以上_碩士生_博士生\n標題： 諮商中心資源教室：【身心障礙者就業資源盤點與就業服務分享講座(場次一)】\n日期： Mon, 9 Sep 2024 07:55:02 +0800\n\u003c/pre\u003e\u003chr class=\"clear-contentunit\"/\u003e\u003ccenter\u003e\u003ch2\u003e活動訊息通知\u003c/h2\u003e\u003c/center\u003e\u003cp\u003e※ 本訊息由系統自動寄出，請勿直接回覆。\u003c/p\u003e\u003cp\u003e※ 如要報名本次活動，請直接點擊右側連結：【\u003ca href=\"https://sys.ndhu.edu.tw/SA/XSL_ApplyRWD/ActApply.aspx?ActID=22366\"\u003e我要報名\u003c/a\u003e】\u003c/p\u003e\u003cp\u003e\u003ctable border=\"1\" width=\"85%\"\u003e\u003ccolgroup\u003e\u003ccol width=\"20%\"/\u003e\u003ccol width=\"80%\"/\u003e\u003c/colgroup\u003e\u003ctbody\u003e\u003ctr\u003e\u003ctd colspan=\"2\"\u003e活動詳細內容\u003c/td\u003e\u003c/tr\u003e\u003ctr bgcolor=\"#D9FFF3\"\u003e\u003ctd\u003e參加對象\u003c/td\u003e\u003ctd\u003e■在校生 ■學士班一年級 ■學士班二年級 ■學士班三年級 ■學士班四年級(含)以上 ■碩士班 ■博士班\u003c/td\u003e\u003c/tr\u003e\u003ctr bgcolor=\"#D9E2F3\"\u003e\u003ctd\u003e活動名稱\u003c/td\u003e\u003ctd\u003e諮商中心資源教室：【身心障礙者就業資源盤點與就業服務分享講座(場次一)】\u003c/td\u003e\u003c/tr\u003e\u003ctr bgcolor=\"#D9FFF3\"\u003e\u003ctd\u003e活動地點\u003c/td\u003e\u003ctd\u003e學生活動中心B102(諮商中心1樓)\u003c/td\u003e\u003c/tr\u003e\u003ctr bgcolor=\"#D9E2F3\"\u003e\u003ctd\u003e報名日期時間\u003c/td\u003e\u003ctd\u003e2024/09/11(三) 00:00 ~ 2024/09/25(三) 11:00\u003c/td\u003e\u003c/tr\u003e\u003ctr bgcolor=\"#D9FFF3\"\u003e\u003ctd\u003e活動日期時間\u003c/td\u003e\u003ctd\u003e2024/09/27(五) 13:30~16:30\u003c/td\u003e\u003c/tr\u003e\u003ctr bgcolor=\"#D9E2F3\"\u003e\u003ctd\u003e活動說明\u003c/td\u003e\u003ctd\u003e\u003cpre\u003e本活動介紹身心障礙者的就業相關資源、各障別職場挑選經驗，\n以及就業成功之經驗分享等，\n以協助同學就業前準備，並認識、掌握所需之就業資源。\n歡迎想了解身心障礙就業資源與職場經驗分享的同學報名參加！\n名額限制 16 位(視報名狀況調整)，報名從速！\n【課程大綱】\n1. 就業資源介紹\n2. 在校期間就業前準備與探索\n3. 理解企業聘用身障者之期待\n4. 各障別職場挑選建議\n5. 成功就業經驗分享\n6. 障礙揭露學\n【講師資訊】：台北市自閉症家長協會-吳靜如 身心障礙者就服督導\u003c/pre\u003e\u003c/td\u003e\u003c/tr\u003e\u003ctr bgcolor=\"#D9FFF3\"\u003e\u003ctd\u003e報名人數\u003c/td\u003e\u003ctd\u003e正取：16人\u003c/td\u003e\u003c/tr\u003e\u003ctr bgcolor=\"#D9E2F3\"\u003e\u003ctd\u003e候補人數\u003c/td\u003e\u003ctd\u003e候補：0人\u003c/td\u003e\u003c/tr\u003e\u003ctr bgcolor=\"#D9FFF3\"\u003e\u003ctd\u003e主辦單位\u003c/td\u003e\u003ctd\u003e心理諮商輔導中心 資源開發組\u003c/td\u003e\u003c/tr\u003e\u003ctr bgcolor=\"#D9E2F3\"\u003e\u003ctd\u003e活動聯絡人\u003c/td\u003e\u003ctd\u003e鍾雅琳\u003c/td\u003e\u003c/tr\u003e\u003ctr bgcolor=\"#D9FFF3\"\u003e\u003ctd\u003e聯絡人電話\u003c/td\u003e\u003ctd\u003e03-8903155\u003c/td\u003e\u003c/tr\u003e\u003ctr bgcolor=\"#D9E2F3\"\u003e\u003ctd\u003e聯絡人Email\u003c/td\u003e\u003ctd\u003elin.chung@gms.ndhu.edu.tw\u003c/td\u003e\u003c/tr\u003e\u003ctr bgcolor=\"#D9FFF3\"\u003e\u003ctd\u003e活動相關網址\u003c/td\u003e\u003ctd\u003e\u003c/td\u003e\u003c/tr\u003e\u003ctr bgcolor=\"#D9E2F3\"\u003e\u003ctd\u003e備註\u003c/td\u003e\u003ctd\u003e【活動注意事項】\n1.活動開始後，遲到逾 15 分鐘者，恕不受理簽到作業。\n2.本活動認證跨域自主學習-多元進取 3 小時。\n3.本活動受限於教材準備與小班制教學，故不開放現場報名。\n4.如有疑問，歡迎來電(03)890-3155詢問鍾老師，或直接於資源教室官方LINE( https://reurl.cc/QdZO9p )詢問。\u003c/td\u003e\u003c/tr\u003e\u003ctr bgcolor=\"#D9FFF3\"\u003e\u003ctd\u003e活動認證項目\u003c/td\u003e\u003ctd\u003e多元進取\u003c/td\u003e\u003c/tr\u003e\u003ctr bgcolor=\"#D9E2F3\"\u003e\u003ctd\u003e活動認證時數\u003c/td\u003e\u003ctd\u003e3.0小時\u003c/td\u003e\u003c/tr\u003e\u003ctr bgcolor=\"#D9FFF3\"\u003e\u003ctd\u003e公務人員終身學習時數\u003c/td\u003e\u003ctd\u003e不提供\u003c/td\u003e\u003c/tr\u003e\u003c/tbody\u003e\u003c/table\u003e\u003c/p\u003e\u003cp\u003e \u003c/p\u003e\u003cp\u003e\n\t\t\n\u003c/p\u003e\u003c/div\u003e",
    "attachments": null
}