{
    "title": "【資料庫公告】Wiley電子書全庫贊助全校師生免費使用三個月",
    "timestamp": "1726639483",
    "url": "mail_display.php?timestamp=1726639483",
    "date": "2024/09/18 14:04",
    "department": "圖書資訊處圖資服務組",
    "author": {
        "department": "圖書資訊處圖資服務組",
        "name": "陳昱佐",
        "email": "yutuchen@gms.ndhu.edu.tw",
        "phone": "6824"
    },
    "content": "\u003cdiv class=\"column1-unit\"\u003e\n\n\u003c!--  信件內容   --\u003e\n\u003cpre\u003e分類： 行政公告, 活動公告, 其他公告\n來源： 圖書資訊處圖資服務組 - 陳昱佐 - yutuchen@gms.ndhu.edu.tw - 電話6824\n對象： 全校教職員_全校學生\n標題： 【資料庫公告】Wiley電子書全庫贊助全校師生免費使用三個月\n日期： Wed, 18 Sep 2024 14:04:43 +0800\n附檔： \u003ca href=\"./message_7/1726639483/Wiley%E4%B8%AD%E8%8B%B1%E6%96%87%E7%B0%A1%E4%BB%8B_0.pdf\" target=\"_blank\"\u003eWiley中英文簡介_0.pdf\u003c/a\u003e (100 KB)   \u003ca href=\"./message_7/1726639483/Wiley%20Online%20Library%E5%B9%B3%E5%8F%B0%E4%BD%BF%E7%94%A8%E6%89%8B%E5%86%8A_%E4%B8%AD%E6%96%87%E7%89%88.pdf\" target=\"_blank\"\u003eWiley Online Library平台使用手冊_中文版.pdf\u003c/a\u003e (2 MB)   \u003ca href=\"./message_7/1726639483/Wiley%20Online%20Library%20uesr%20guide_eng.pdf\" target=\"_blank\"\u003eWiley Online Library uesr guide_eng.pdf\u003c/a\u003e (6 MB)   \u003c/pre\u003e\u003chr class=\"clear-contentunit\"/\u003e\u003cpre\u003eWiley電子書全庫，贊助全校師生免費使用三個月，書量約24,541種，讓全校師生可24hrs利用資源，歡迎師生廣為利用。\n\n平台URL:\n\n\u003ca href=\"https://onlinelibrary.wiley.com/\" target=\"_blank\"\u003ehttps://onlinelibrary.wiley.com/\u003c/a\u003e\n\n書單URL:\n\n\u003ca href=\"https://docs.google.com/spreadsheets/d/1tH1sAJuBh9Lr4uUQMnJK4Ee8EDrHIY9c/edit?usp=drive_link\u0026amp;ouid=111811035494940022666\u0026amp;rtpof=true\u0026amp;sd=true\" target=\"_blank\"\u003ehttps://docs.google.com/spreadsheets/d/1tH1sAJuBh9Lr4uUQMnJK4Ee8EDrHIY9c/edit?usp=drive_link\u0026amp;ouid=111811035494940022666\u0026amp;rtpof=true\u0026amp;sd=true\u003c/a\u003e\n\n試用期間:2024/9/16-2024/12/15\n\n校外使用請利用SSL-VPN連線使用。\n\nWiley電子書有獎徵答活動預告:2024/9/23～2024/10/22\n\n屆時歡迎踴躍參加。\u003c/pre\u003e\u003chr/\u003ejpg、png、gif、pdf 附檔縮圖（pdf 只顯示第一頁）：\u003cp\u003e\u003c/p\u003e\u003cdiv style=\"text-align:center;display:inline-block;margin-right:20px;\"\u003e\u003ca href=\"./message_7/1726639483/Wiley%E4%B8%AD%E8%8B%B1%E6%96%87%E7%B0%A1%E4%BB%8B_0.pdf\" target=\"_blank\"\u003e\u003cimg src=\"./thumb/1726639483_Wiley中英文簡介_0.pdf.jpg\"/\u003e\u003c/a\u003e\u003cbr/\u003eWiley中英文簡介_0.pdf\u003c/div\u003e\u003cdiv style=\"text-align:center;display:inline-block;margin-right:20px;\"\u003e\u003ca href=\"./message_7/1726639483/Wiley%20Online%20Library%E5%B9%B3%E5%8F%B0%E4%BD%BF%E7%94%A8%E6%89%8B%E5%86%8A_%E4%B8%AD%E6%96%87%E7%89%88.pdf\" target=\"_blank\"\u003e\u003cimg src=\"./thumb/1726639483_Wiley Online Library平台使用手冊_中文版.pdf.jpg\"/\u003e\u003c/a\u003e\u003cbr/\u003eWiley Online Library平台使用手冊_中文版.pdf\u003c/div\u003e\u003cdiv style=\"text-align:center;display:inline-block;margin-right:20px;\"\u003e\u003ca href=\"./message_7/1726639483/Wiley%20Online%20Library%20uesr%20guide_eng.pdf\" target=\"_blank\"\u003e\u003cimg src=\"./thumb/1726639483_Wiley Online Library uesr guide_eng.pdf.jpg\"/\u003e\u003c/a\u003e\u003cbr/\u003eWiley Online Library uesr guide_eng.pdf\u003c/div\u003e\n\t\t\n\u003c/div\u003e",
    "attachments": [
        {
            "fileName": "Wiley中英文簡介_0.pdf",
            "fileSize": "(6 MB)",
            "filePath": "./message_7/1726639483/Wiley%E4%B8%AD%E8%8B%B1%E6%96%87%E7%B0%A1%E4%BB%8B_0.pdf",
            "thumbPath": "/thumb/1726639483_Wiley%E4%B8%AD%E8%8B%B1%E6%96%87%E7%B0%A1%E4%BB%8B_0.pdf.jpg"
        },
        {
            "fileName": "Wiley Online Library平台使用手冊_中文版.pdf",
            "fileSize": "(6 MB)",
            "filePath": "./message_7/1726639483/Wiley%20Online%20Library%E5%B9%B3%E5%8F%B0%E4%BD%BF%E7%94%A8%E6%89%8B%E5%86%8A_%E4%B8%AD%E6%96%87%E7%89%88.pdf",
            "thumbPath": "/thumb/1726639483_Wiley%20Online%20Library%E5%B9%B3%E5%8F%B0%E4%BD%BF%E7%94%A8%E6%89%8B%E5%86%8A_%E4%B8%AD%E6%96%87%E7%89%88.pdf.jpg"
        },
        {
            "fileName": "Wiley Online Library uesr guide_eng.pdf",
            "fileSize": "(6 MB)",
            "filePath": "./message_7/1726639483/Wiley%20Online%20Library%20uesr%20guide_eng.pdf",
            "thumbPath": "/thumb/1726639483_Wiley%20Online%20Library%20uesr%20guide_eng.pdf.jpg"
        },
        {
            "fileName": "https://onlinelibrary.wiley.com/",
            "fileSize": "試用期間:2024/9/16-2024/12/15\n\n校外使用請利用SSL-VPN連線使用。\n\nWiley電子書有獎徵答活動預告:2024/9/23～2024/10/22\n\n屆時歡迎踴躍參加。",
            "filePath": "https://onlinelibrary.wiley.com/",
            "thumbPath": null
        },
        {
            "fileName": "https://docs.google.com/spreadsheets/d/1tH1sAJuBh9Lr4uUQMnJK4Ee8EDrHIY9c/edit?usp=drive_link\u0026ouid=111811035494940022666\u0026rtpof=true\u0026sd=true",
            "fileSize": "試用期間:2024/9/16-2024/12/15\n\n校外使用請利用SSL-VPN連線使用。\n\nWiley電子書有獎徵答活動預告:2024/9/23～2024/10/22\n\n屆時歡迎踴躍參加。",
            "filePath": "https://docs.google.com/spreadsheets/d/1tH1sAJuBh9Lr4uUQMnJK4Ee8EDrHIY9c/edit?usp=drive_link\u0026ouid=111811035494940022666\u0026rtpof=true\u0026sd=true",
            "thumbPath": null
        }
    ]
}