{
    "title": "管理學院國際學士班聯合迎新",
    "timestamp": "1734479702",
    "url": "mail_display.php?timestamp=1734479702",
    "date": "2024/12/18 07:55",
    "department": "管理學院",
    "author": {
        "department": "管理學院",
        "name": "郭娜",
        "email": "inagn@gms.ndhu.edu.tw",
        "phone": "03-8903007"
    },
    "content": "\u003cdiv class=\"column1-unit\"\u003e\n\n\u003c!--  信件內容   --\u003e\n\u003cpre\u003e分類： 活動公告\n來源： 管理學院 - 郭娜 - inagn@gms.ndhu.edu.tw - 電話03-8903007\n對象： 僅限本院學生\n標題： 管理學院國際學士班聯合迎新\n日期： Wed, 18 Dec 2024 07:55:02 +0800\n\u003c/pre\u003e\u003chr class=\"clear-contentunit\"/\u003e\u003ccenter\u003e\u003ch2\u003e活動訊息通知\u003c/h2\u003e\u003c/center\u003e\u003cp\u003e※ 本訊息由系統自動寄出，請勿直接回覆。\u003c/p\u003e\u003cp\u003e※ 如要報名本次活動，請直接點擊右側連結：【\u003ca href=\"https://sys.ndhu.edu.tw/SA/XSL_ApplyRWD/ActApply.aspx?ActID=23737\"\u003e我要報名\u003c/a\u003e】\u003c/p\u003e\u003cp\u003e\u003ctable border=\"1\" width=\"85%\"\u003e\u003ccolgroup\u003e\u003ccol width=\"20%\"/\u003e\u003ccol width=\"80%\"/\u003e\u003c/colgroup\u003e\u003ctbody\u003e\u003ctr\u003e\u003ctd colspan=\"2\"\u003e活動詳細內容\u003c/td\u003e\u003c/tr\u003e\u003ctr bgcolor=\"#D9FFF3\"\u003e\u003ctd\u003e參加對象\u003c/td\u003e\u003ctd\u003e■僅限本院學生\u003c/td\u003e\u003c/tr\u003e\u003ctr bgcolor=\"#D9E2F3\"\u003e\u003ctd\u003e活動名稱\u003c/td\u003e\u003ctd\u003e管理學院國際學士班聯合迎新\u003c/td\u003e\u003c/tr\u003e\u003ctr bgcolor=\"#D9FFF3\"\u003e\u003ctd\u003e活動地點\u003c/td\u003e\u003ctd\u003e管理學院（正門）\u003c/td\u003e\u003c/tr\u003e\u003ctr bgcolor=\"#D9E2F3\"\u003e\u003ctd\u003e報名日期時間\u003c/td\u003e\u003ctd\u003e2024/12/17(二) 12:00 ~ 2024/12/20(五) 00:00\u003c/td\u003e\u003c/tr\u003e\u003ctr bgcolor=\"#D9FFF3\"\u003e\u003ctd\u003e活動日期時間\u003c/td\u003e\u003ctd\u003e2024/12/21(六) 15:00~17:00\u003c/td\u003e\u003c/tr\u003e\u003ctr bgcolor=\"#D9E2F3\"\u003e\u003ctd\u003e活動說明\u003c/td\u003e\u003ctd\u003e\u003cpre\u003e親愛的同學們，\n我們誠摯邀請您參加國際學士班的聯合迎新活動！這不僅是迎接新學期的好機會，更是促進同學間交流的絕佳平台。：\n活動中，您將欣賞到各類精彩表演，感受迎新的歡樂氛圍。此外，還有有趣的闖關活動，等著大家前來挑戰。所有參加者都有機會參加抽獎，獲得豐富的獎品！活動期間，我們也將提供各式美味點心哦。期待您的參加，讓我們一起在聖誕季節的渲染下，建立深厚的友誼！\u003c/pre\u003e\u003c/td\u003e\u003c/tr\u003e\u003ctr bgcolor=\"#D9FFF3\"\u003e\u003ctd\u003e報名人數\u003c/td\u003e\u003ctd\u003e正取：100人\u003c/td\u003e\u003c/tr\u003e\u003ctr bgcolor=\"#D9E2F3\"\u003e\u003ctd\u003e候補人數\u003c/td\u003e\u003ctd\u003e候補：0人\u003c/td\u003e\u003c/tr\u003e\u003ctr bgcolor=\"#D9FFF3\"\u003e\u003ctd\u003e主辦單位\u003c/td\u003e\u003ctd\u003e管理學院 國際事務中心\u003c/td\u003e\u003c/tr\u003e\u003ctr bgcolor=\"#D9E2F3\"\u003e\u003ctd\u003e活動聯絡人\u003c/td\u003e\u003ctd\u003e郭娜\u003c/td\u003e\u003c/tr\u003e\u003ctr bgcolor=\"#D9FFF3\"\u003e\u003ctd\u003e聯絡人電話\u003c/td\u003e\u003ctd\u003e03-8903007\u003c/td\u003e\u003c/tr\u003e\u003ctr bgcolor=\"#D9E2F3\"\u003e\u003ctd\u003e聯絡人Email\u003c/td\u003e\u003ctd\u003einagn@gms.ndhu.edu.tw\u003c/td\u003e\u003c/tr\u003e\u003ctr bgcolor=\"#D9FFF3\"\u003e\u003ctd\u003e活動相關網址\u003c/td\u003e\u003ctd\u003e\u003c/td\u003e\u003c/tr\u003e\u003ctr bgcolor=\"#D9E2F3\"\u003e\u003ctd\u003e備註\u003c/td\u003e\u003ctd\u003e參加對象僅限管理科學與財金國際學士學位學程，會計與資訊管理國際學士班，數位行銷與服務創新國際學士班之學生\u003c/td\u003e\u003c/tr\u003e\u003ctr bgcolor=\"#D9FFF3\"\u003e\u003ctd\u003e活動認證項目\u003c/td\u003e\u003ctd\u003e多元進取\u003c/td\u003e\u003c/tr\u003e\u003ctr bgcolor=\"#D9E2F3\"\u003e\u003ctd\u003e活動認證時數\u003c/td\u003e\u003ctd\u003e2.0小時\u003c/td\u003e\u003c/tr\u003e\u003ctr bgcolor=\"#D9FFF3\"\u003e\u003ctd\u003e公務人員終身學習時數\u003c/td\u003e\u003ctd\u003e不提供\u003c/td\u003e\u003c/tr\u003e\u003c/tbody\u003e\u003c/table\u003e\u003c/p\u003e\u003cp\u003e \u003c/p\u003e\u003cp\u003e\n\t\t\n\u003c/p\u003e\u003c/div\u003e",
    "attachments": null
}