[
    {
        "title": "【教卓中心】112-2學期教學助理(TA training courses )培訓課程開始報名囉~",
        "timestamp": "1708068518",
        "url": "mail_display.php?timestamp=1708068518",
        "date": "2024/02/16 15:28",
        "department": "教學卓越中心",
        "author": "游家盛"
    },
    {
        "title": "112-2學期學生自主學習培力方案通過名單",
        "timestamp": "1708067233",
        "url": "mail_display.php?timestamp=1708067233",
        "date": "2024/02/16 15:07",
        "department": "教學卓越中心",
        "author": "鄭宏昱"
    },
    {
        "title": "圖書服務-KMOVIE影音平台試用公告",
        "timestamp": "1708066773",
        "url": "mail_display.php?timestamp=1708066773",
        "date": "2024/02/16 14:59",
        "department": "圖書資訊處圖資服務組",
        "author": "陳昱佐"
    },
    {
        "title": "【課務組公告】請注意網路加退選時間  Please Notice the Period for Online Add/Drop Courses",
        "timestamp": "1708064081",
        "url": "mail_display.php?timestamp=1708064081",
        "date": "2024/02/16 14:14",
        "department": "教務處課務組",
        "author": "課務組"
    },
    {
        "title": "【通識】112-2學期通識課程活動補助申請(第三次公告)",
        "timestamp": "1708062419",
        "url": "mail_display.php?timestamp=1708062419",
        "date": "2024/02/16 13:46",
        "department": "通識教育中心",
        "author": "李睿芬"
    },
    {
        "title": "修正「全國軍公教員工待遇支給要點」第4點附表8「公教人員婚喪生育補助表」，並自113年1月5日生效",
        "timestamp": "1708056639",
        "url": "mail_display.php?timestamp=1708056639",
        "date": "2024/02/16 12:10",
        "department": "人事室",
        "author": "張琇茹"
    },
    {
        "title": "【縱目歐亞-空間與人文的對話】講座_2/21（三）四方之眼-歐洲、日本、朝鮮、大明等歐亞四方之人筆下的大運河",
        "timestamp": "1708056535",
        "url": "mail_display.php?timestamp=1708056535",
        "date": "2024/02/16 12:08",
        "department": "人文社會科學學院",
        "author": "姜妃澤"
    },
    {
        "title": "【公告】有關附設實驗國民小學辦理113學年度一年級新生暨附設幼兒園新生登記入學事宜，請本校教職員工有意願登記者，於本(113)年3月6日(星期三)前將相關資料寄送至人事室。",
        "timestamp": "1708053701",
        "url": "mail_display.php?timestamp=1708053701",
        "date": "2024/02/16 11:21",
        "department": "人事室",
        "author": "劉依虹"
    },
    {
        "title": "教育部青年發展署辦理113年「大專生公部門見習計畫」及「經濟自立青年工讀計畫」",
        "timestamp": "1708048985",
        "url": "mail_display.php?timestamp=1708048985",
        "date": "2024/02/16 10:03",
        "department": "學務處畢業生及校友服務組",
        "author": "黃文雯"
    },
    {
        "title": "【課務組】112-2學期兼任教師教學、課程停開及請假補（代）課提醒事項",
        "timestamp": "1708047894",
        "url": "mail_display.php?timestamp=1708047894",
        "date": "2024/02/16 09:44",
        "department": "教務處課務組",
        "author": "宋育縈"
    },
    {
        "title": "【公告】國立中興大學辦理第28屆傑出校友遴選，請惠予推薦人選。",
        "timestamp": "1708047443",
        "url": "mail_display.php?timestamp=1708047443",
        "date": "2024/02/16 09:37",
        "department": "人事室",
        "author": "張淑慧"
    },
    {
        "title": "【實體】第一部曲：永續報告書重要篇章--認識永續管理標準—GRI",
        "timestamp": "1708041301",
        "url": "mail_display.php?timestamp=1708041301",
        "date": "2024/02/16 07:55",
        "department": "永續發展中心籌備處",
        "author": "李莉莉"
    },
    {
        "title": "全球視野，在地培育——臺越雙語實作招募說明會",
        "timestamp": "1707986551",
        "url": "mail_display.php?timestamp=1707986551",
        "date": "2024/02/15 16:42",
        "department": "教育與潛能開發學系",
        "author": "李宣誼"
    },
    {
        "title": "112-2學產基金低收入戶學生助學金申請",
        "timestamp": "1707983968",
        "url": "mail_display.php?timestamp=1707983968",
        "date": "2024/02/15 15:59",
        "department": "學務處生活輔導組",
        "author": "李欣憓"
    },
    {
        "title": "113年度校區內客貨電梯進行月保養排程通告 (2月保養)",
        "timestamp": "1707982962",
        "url": "mail_display.php?timestamp=1707982962",
        "date": "2024/02/15 15:42",
        "department": "總務處營繕組",
        "author": "劉宏銘"
    }
]