[
    {
        "title": "【亭午風起，有詩東華】112-2 英詩小講堂 5/01 第4場 \"Lyrical Lunch at Dong Hwa\" Poetry Reading Session 4",
        "timestamp": "1713743705",
        "url": "mail_display.php?timestamp=1713743705",
        "date": "2024/04/22 07:55",
        "department": "洄瀾學院 語言中心",
        "author": "呂岳芳"
    },
    {
        "title": "【法語角】French Movie Nights 法國電影之夜 Session 3：5/29《天才警官 Le Gendarme de Saint-Tropez》(1964)",
        "timestamp": "1713743704",
        "url": "mail_display.php?timestamp=1713743704",
        "date": "2024/04/22 07:55",
        "department": "洄瀾學院 語言中心",
        "author": "呂岳芳"
    },
    {
        "title": "【112族文週「族探」系列活動】開幕茶會",
        "timestamp": "1713743703",
        "url": "mail_display.php?timestamp=1713743703",
        "date": "2024/04/22 07:55",
        "department": "原住民民族學院 族群關係與文化學系",
        "author": "黃淑美"
    },
    {
        "title": "電影之夜",
        "timestamp": "1713743702",
        "url": "mail_display.php?timestamp=1713743702",
        "date": "2024/04/22 07:55",
        "department": "原住民民族學院 族群關係與文化學系",
        "author": "黃淑美"
    },
    {
        "title": "【112族文週「族碳」系列活動】文化走讀：探族跡",
        "timestamp": "1713743701",
        "url": "mail_display.php?timestamp=1713743701",
        "date": "2024/04/22 07:55",
        "department": "原住民民族學院 族群關係與文化學系",
        "author": "黃淑美"
    },
    {
        "title": "系演講－幼幼！我的未來不是夢",
        "timestamp": "1713657303",
        "url": "mail_display.php?timestamp=1713657303",
        "date": "2024/04/21 07:55",
        "department": "花師教育學院 幼兒教育學系",
        "author": "蕭羽芩"
    },
    {
        "title": "歷史學系專題演講：戰後臺灣情治機關的建置與演變",
        "timestamp": "1713657302",
        "url": "mail_display.php?timestamp=1713657302",
        "date": "2024/04/21 07:55",
        "department": "人文社會科學學院 歷史學系",
        "author": "吳芷萱"
    },
    {
        "title": "【企管系暨運籌所】112-2 Language Lounge-Book or Movie Club(第五場)",
        "timestamp": "1713570908",
        "url": "mail_display.php?timestamp=1713570908",
        "date": "2024/04/20 07:55",
        "department": "管理學院 企業管理學系",
        "author": "陳雅芳"
    },
    {
        "title": "【企管系專題講座】生涯講座(南山人壽 順橙通訊處)",
        "timestamp": "1713570907",
        "url": "mail_display.php?timestamp=1713570907",
        "date": "2024/04/20 07:55",
        "department": "管理學院 企業管理學系",
        "author": "陳雅芳"
    },
    {
        "title": "校友回娘家-走在文化的這條路上",
        "timestamp": "1713570906",
        "url": "mail_display.php?timestamp=1713570906",
        "date": "2024/04/20 07:55",
        "department": "學務處 原住民族學生資源中心",
        "author": "吳倩茹"
    },
    {
        "title": "口腔與身心健康系列講座",
        "timestamp": "1713570905",
        "url": "mail_display.php?timestamp=1713570905",
        "date": "2024/04/20 07:55",
        "department": "學務處 衛生保健組",
        "author": "吳星穎"
    },
    {
        "title": "113學年度(第10屆)公益專班線上說明會",
        "timestamp": "1713570904",
        "url": "mail_display.php?timestamp=1713570904",
        "date": "2024/04/20 07:55",
        "department": "管理學院 財務金融學系",
        "author": "蔡季諭"
    },
    {
        "title": "「縱目歐亞-空間與人文的對話」課程系列講座-5/8（三）賀喜副教授（香港中文大學歷史系）：走出書齋看歷史：東亞社會的宗族與系譜",
        "timestamp": "1713570903",
        "url": "mail_display.php?timestamp=1713570903",
        "date": "2024/04/20 07:55",
        "department": "人文社會科學學院 ",
        "author": "姜妃澤"
    },
    {
        "title": "反歧視系列｜超越偏見：打破精神疾病汙名化的現象",
        "timestamp": "1713570902",
        "url": "mail_display.php?timestamp=1713570902",
        "date": "2024/04/20 07:55",
        "department": "人文社會科學學院 諮商與臨床心理學系",
        "author": "徐青卉"
    },
    {
        "title": "反歧視系列｜超越偏見：打破精神疾病汙名化的現象",
        "timestamp": "1713570901",
        "url": "mail_display.php?timestamp=1713570901",
        "date": "2024/04/20 07:55",
        "department": "人文社會科學學院 諮商與臨床心理學系",
        "author": "徐青卉"
    }
]